README
setup.py
Podis.egg-info/PKG-INFO
Podis.egg-info/SOURCES.txt
Podis.egg-info/dependency_links.txt
Podis.egg-info/not-zip-safe
Podis.egg-info/top_level.txt
podis/__init__.py
podis/api.py
podis/lib.py