Metadata-Version: 1.0
Name: Podis
Version: 2.3
Summary: Retrieve INSEE codes of french territories from their postal distributions
Home-page: http://packages.python.org/Podis/
Author: Romain Soufflet
Author-email: podis@infos-pratiques.org
License: http://www.fsf.org/licensing/licenses/agpl-3.0.html
Keywords: code depcom insee postal routing
Platform: UNKNOWN
Classifier: Development Status :: 5 - Production/Stable
Classifier: Environment :: Console
Classifier: Intended Audience :: Information Technology
Classifier: License :: OSI Approved :: GNU Affero General Public License v3
Classifier: Operating System :: OS Independent
Classifier: Programming Language :: Python
